{
    "0": 8,
    "1": 6,
    "3": 8,
    "4": 3,
    "5": 3,
    "6": 4,
    "7": 3,
    "8": 1,
    "9": 4,
    "10": 1,
    "11": 1,
    "12": 4,
    "13": 3,
    "15": 1,
    "16": 4,
    "18": 1,
    "19": 2,
    "20": 3,
    "21": 2,
    "22": 1,
    "23": 1,
    "24": 3,
    "27": 87,
    "28": 1,
    "29": 60,
    "30": 14,
    "32": 1,
    "33": 1,
    "34": 1,
    "39": 1,
    "40": 1,
    "43": 1,
    "45": 30,
    "52": 1,
    "55": 2,
    "77": 1,
    "79": 8,
    "127": 32,
    "276": 1,
    "1000": 1,
    "1056": 1,
    "1100": 1,
    "1130": 1,
    "1200": 1,
    "1230": 1,
    "1248": 1,
    "1301": 1,
    "1313": 1,
    "1350": 1,
    "1353": 1,
    "1400": 1,
    "1442": 1,
    "1530": 1,
    "1538": 1,
    "1557": 30,
    "1558": 1,
    "1600": 1,
    "1716": 1,
    "1731": 1,
    "1745": 1,
    "1806": 1,
    "1830": 30,
    "1840": 1,
    "1851": 1,
    "1853": 1,
    "1910": 1,
    "1927": 1,
    "1937": 1,
    "1945": 1,
    "2001": 30,
    "2017": 62,
    "2209": 30,
    "2306": 30,
    "2389": 1,
    "8570": 4,
    "miklar": 1,
    "að": 56,
    "fréttir": 4,
    "Þannig": 1,
    "Í": 2,
    "menn": 1,
    "varaformaður": 1,
    "Á": 1,
    "Því": 1,
    "ferðamenn": 1,
    "Ekki": 1,
    "þetta": 4,
    "Menn": 1,
    "Norskt": 30,
    "áhyggjur": 30,
    "viðskiptablað": 30,
    "annarri": 30,
    "Varaformaður": 27,
    "vísar": 30,
    "bug": 30,
    "framundan": 30,
    "gengið": 30,
    "frammi": 30,
    "atvinnugreinin": 30,
    "kallar": 31,
    "aðgerðum": 30,
    "gengisflökti": 30,
    "Undanfarið": 30,
    "íslenskri": 30,
    "bankarnir": 30,
    "dregið": 30,
    "útlánum": 30,
    "hótelafyrirtækja": 30,
    "úr": 34,
    "landsbyggðinni": 30,
    "birst": 30,
    "kortavelta": 30,
    "erlendra": 30,
    "ferðamanna": 30,
    "minnkað": 30,
    "styrkingar": 30,
    "síst": 30,
    "viðskiptablaðinu": 30,
    "Dagens": 30,
    "Næringsliv": 30,
    "umfjöllun": 3,
    "óttist": 30,
    "hafi": 30,
    "tryggt": 30,
    "viðsnúning": 30,
    "nýja": 30,
    "svona": 31,
    "hraður": 30,
    "skömmum": 30,
    "tíma": 88,
    "sjálfbær": 30,
    "staðan": 30,
    "bankahrunið": 30,
    "viðkvæm": 30,
    "hátt": 30,
    "vissan": 30,
    "miður": 30,
    "mikill": 30,
    "höfðum": 30,
    "raungerast": 30,
    "síðasta": 31,
    "þegar": 34,
    "umræðan": 30,
    "virðisaukaskatt": 30,
    "vetur": 30,
    "hæst": 30,
    "íslensku": 31,
    "klárlega": 30,
    "núna": 31,
    "komnar": 30,
    "Ferðamenn": 7,
    "gengisstyrkingar": 30,
    "spáð": 30,
    "eyða": 30,
    "dveljast": 30,
    "skemur": 30,
    "fara": 30,
    "ákveðið": 30,
    "land": 30,
    "áhyggjuefni": 30,
    "Er": 30,
    "yfirvofandi": 30,
    "afkomubrests": 30,
    "Nei": 30,
    "held": 30,
    "getur": 30,
    "niðursveifla": 30,
    "upplifðum": 30,
    "svipuð": 30,
    "mjög": 31,
    "gott": 31,
    "ár": 31,
    "árið": 30,
    "2000.": 30,
    "gengi": 30,
    "stjórnvöld": 30,
    "því.": 30,
    "bara": 30,
    "alveg": 30,
    "nauðsynlegt": 30,
    "stoppa": 30,
    "talað": 30,
    "stýrivexti": 30,
    "mikil": 30,
    "verður": 31,
    "Seðlabankinn": 30,
    "girða": 30,
    "öllum": 31,
    "tiltækum": 30,
    "ráðum": 30,
    "böndum": 30,
    "Stýrivextir": 30,
    "brók": 30,
    "sig": 31,
    "meginvextir": 30,
    "sjö": 30,
    "daga": 31,
    "bundnum": 30,
    "innlánum": 30,
    "lánastofnana": 30,
    "hjá": 31,
    "voru": 31,
    "lækkaðir": 30,
    "þessir": 30,
    "025": 30,
    "prósentur": 30,
    "prósent": 32,
    "14.": 30,
    "júní": 31,
    "vaxtaákvörðunardagur": 30,
    "peningastefnunefndar": 30,
    "Næsti": 30,
    "23.": 30,
    "síðastliðinn": 31,
    "ágúst": 31,
    "næstkomandi": 30,
    "Staða": 85,
    "Marels": 85,
    "aldrei": 88,
    "sterkari": 85,
    "rúman": 35,
    "milljarð": 35,
    "Valitor": 34,
    "varar": 33,
    "svikatölvupóstum": 32,
    "Íslendingar": 31,
    "hættir": 31,
    "kaupa": 31,
    "Seachill": 31,
    "ársins": 33,
    "Þá": 1,
    "hann": 1,
    "þrátt": 1,
    "Við": 1,
    "hætta": 1,
    "stúlku": 1,
    "mér": 1,
    "talinn": 1,
    "SPORT": 1,
    "Nýlegt": 1,
    "Vettel": 1,
    "unnið": 1,
    "ráspól": 1,
    "Formúla": 1,
    "þessum": 1,
    "stefnir": 1,
    "sigurinn": 1,
    "baráttu": 1,
    "opna": 1,
    "meistaramótinu": 1,
    "kanadíska": 1,
    "harða": 1,
    "Svíþjóð": 1,
    "mættust": 1,
    "liða": 1,
    "átta": 1,
    "úrslitum": 1,
    "kvenna": 1,
    "sviðið": 1,
    "átti": 1,
    "ungverska": 1,
    "kappaksturinn": 1,
    "Formúlu": 1,
    "Búrið": 1,
    "handklæðið": 1,
    "tímatöku": 1,
    "svindla": 1,
    "vigtinni": 1,
    "Notaði": 1,
    "franska": 1,
    "ofurbikarnum": 1,
    "Balí": 1,
    "Strákasaga": 1,
    "Saga": 1,
    "falla": 1,
    "Allir": 1,
    "Garðarsdóttir": 1,
    "höfum": 1,
    "gert": 1,
    "Þórlindur": 1,
    "Kjartansson": 1,
    "Hvað": 1,
    "verðskulda": 1,
    "28.07.17": 1,
    "Vestfirðinga": 1,
    "Gísli": 1,
    "Valtað": 1,
    "Sigurðsson": 1,
    "æskunni": 1,
    "frelsinu": 1,
    "FÓTBOLTI": 1,
    "Ávextir": 1,
    "svalasta": 1,
    "MATUR": 1,
    "Lögreglan": 1,
    "ósáttra": 1,
    "farþega": 1,
    "Herjólfi": 1,
    "ber": 1,
    "ferðir": 1,
    "Delevingne": 1,
    "fjórar": 1,
    "erfðablöndun": 1,
    "tengjast": 1,
    "starfandi": 1,
    "fiskeldisstöðvum": 1,
    "nýtt": 1,
    "Pharrell": 1,
    "flækja": 1,
    "lífið": 1,
    "óþörfu": 1,
    "Selfoss": 1,
    "fær": 1,
    "unglingalandsliðsmann": 1,
    "HANDBOLTI": 1,
    "Stundum": 1,
    "stemning": 1,
    "Frábær": 1,
    "druslupeppi": 1,
    "frábæran": 1,
    "árangur": 1,
    "utan": 1,
    "KÖRFUBOLTI": 1,
    "Manndráp": 1,
    "Elvar": 1,
    "þrýst": 1,
    "brjósthol": 1,
    "mannsins": 1,
    "tekið": 1,
    "hálstaki": 1,
    "næturgistingu": 1,
    "Mosfellsdal": 1,
    "bílastæðum": 1,
    "líkamanum": 1,
    "Inter": 1,
    "Farið": 1,
    "möguleika": 1,
    "Vinsælar": 1,
    "klippur": 1,
    "vegaköntum": 1,
    "Umræða": 1,
    "Inkassodeildina": 1,
    "jökulhlaupi": 1,
    "FH": 1,
    "ósk": 1,
    "Ræða": 1,
    "samfélaginu": 1,
    "viðhorfið": 1,
    "þyki": 1,
    "undarlegt": 1,
    "þolendum": 1,
    "Mar": 1,
    "stafræns": 1,
    "kenna": 1,
    "nokkur": 1,
    "ofbeldið": 1,
    "varð": 1,
    "ummæli": 1,
    "þykja": 1,
    "þolendaskömmun": 1,
    "Ummæli": 1,
    "þann": 1,
    "kynferðisofbeldis": 1,
    "konur": 1,
    "forðast": 1,
    "klæða": 1,
    "skyldu": 1,
    "viðhafði": 1,
    "þeim": 1,
    "tilgangi": 1,
    "kynferðisofbeldi": 1,
    "umdeildu": 1,
    "urðu": 1,
    "einmitt": 1,
    "Duslugangan": 1,
    "hóf": 1,
    "druslur": 1,
    "göngu": 1,
    "sína": 1,
    "apríl": 1,
    "Ummælin": 1,
    "rólegir": 1,
    "jökulhlaupinu": 1,
    "Snorri": 1,
    "grunnbúðir": 1,
    "Íslenska": 1,
    "vann": 1,
    "öruggan": 1,
    "2011.": 1,
    "belgíska": 1,
    "Akranesi": 1,
    "leikur": 1,
    "karlalandsliðið": 1,
    "heimavelli": 1,
    "hefst": 1,
    "31.": 1,
    "íslenska": 1,
    "Helgi": 1,
    "Gerðum": 1,
    "betur": 1,
    "síðast": 1,
    "liðsins": 1,
    "spilaði": 1,
    "leikinn": 1,
    "öðru": 1,
    "Haukur": 1,
    "Grasshopper": 1,
    "efstur": 1,
    "Bóasson": 1,
    "Rúnar": 1,
    "Borgunarbikarmótinu": 1,
    "Ólafía": 1,
    "tapi": 1,
    "skorinu": 1,
    "halda": 1,
    "nálægt": 1,
    "Annar": 1,
    "lokahringinn": 1,
    "U18": 1,
    "Íslands": 1,
    "Bætti": 1,
    "Aðalmálið": 1,
    "komst": 1,
    "Herthu": 1,
    "Öruggur": 1,
    "tryggði": 1,
    "undanúrslitin": 1,
    "Reyndi": 1,
    "Íslandsmetið": 1,
    "skemmtistaði": 1,
    "klæddur": 1,
    "riddari": 1,
    "sumum": 1,
    "sæti": 1,
    "ákveðin": 1,
    "skilyrði": 1,
    "varðandi": 1,
    "klæðaburð": 1,
    "ferðalag": 1,
    "hugmyndaheim": 1,
    "samfélag": 1,
    "Gagnrýni": 1,
    "Vildi": 1,
    "skemmtistöðum": 1,
    "helst": 1,
    "handbolta": 1,
    "Fjörugt": 1,
    "úti": 1,
    "fyllir": 1,
    "víðáttunni": 1,
    "hugsjónir": 1,
    "bak": 1,
    "frelsistilfinningu": 1,
    "mig": 1,
    "sýningu": 1,
    "Menning": 1,
    "Allra": 1,
    "þessa": 1,
    "hlaupa": 1,
    "sumarvinnan": 1,
    "Hugarórar": 1,
    "frönsku": 1,
    "vændishúsi": 1,
    "óendanlega": 1,
    "Ljósið": 1,
    "mikilvægt": 1,
    "kynningar": 1,
    "besta": 1,
    "Group": 1,
    "birti": 1,
    "félagið": 1,
    "uppgjör": 1,
    "0930": 1,
    "fjórðung": 1,
    "tekjuvöxt": 1,
    "Búast": 1,
    "annan": 1,
    "aukinni": 1,
    "samkeppni": 1,
    "0700": 1,
    "má": 1,
    "af": 63,
    "kreppu": 60,
    "stjórnar": 60,
    "Samtaka": 60,
    "Hann": 60,
    "óvissan": 60,
    "stærsta": 60,
    "því": 65,
    "frá": 65,
    "vandamálið": 60,
    "Seðlabankanum": 60,
    "bregðast": 60,
    "blikur": 61,
    "lofti": 61,
    "norska": 60,
    "Þar": 5,
    "vöxtur": 60,
    "efnahagslífinu": 60,
    "Garðarsson": 60,
    "var": 63,
    "áhrif": 60,
    "fram": 61,
    "minna": 60,
    "verði": 62,
    "flökt": 60,
    "krónunni": 60,
    "Seðlabankans": 60,
    "vextir": 60,
    "hinn": 60,
    "Tweet": 61,
    "hagnaðist": 63,
    "Fleiri": 61,
    "fyrri": 62,
    "Sjá": 61,
    "hluta": 62,
    "meira": 61,
    "þar": 2,
    "Allt": 2,
    "Stúlku": 2,
    "Leigurisarnir": 8,
    "íbúðir": 8,
    "beinni": 2,
    "Bræðslan": 2,
    "Dýrmætur": 2,
    "tími": 2,
    "spillis": 2,
    "krabbameinsveikra": 2,
    "TÓNLIST": 2,
    "Myndir": 2,
    "Vísi": 2,
    "Mörkin": 2,
    "leik": 2,
    "Léttur": 2,
    "Bandaríkjunum": 2,
    "Leikur": 2,
    "barnapúður": 2,
    "endaði": 2,
    "illa": 2,
    "Leik": 2,
    "Danmerkur": 2,
    "Þýskalands": 2,
    "frestað": 2,
    "morguns": 2,
    "Eitt": 2,
    "óvenjulegasta": 2,
    "jafnfram": 2,
    "fallegasta": 2,
    "sjálfsmark": 2,
    "Evrópumóti": 2,
    "Tónlist": 2,
    "Zlatan": 2,
    "Evrópu": 2,
    "Gylfa": 2,
    "leysist": 2,
    "fljótlega": 2,
    "búin": 2,
    "mál": 2,
    "raka": 2,
    "sigruðu": 2,
    "býst": 2,
    "Bakþankar": 2,
    "hárið": 2,
    "Berjumst": 2,
    "skæruhernaði": 2,
    "Sigmarsdóttir": 2,
    "jafnrétti": 2,
    "29.07.17": 2,
    "Myglaðir": 2,
    "leikskólar": 2,
    "Sirrý": 2,
    "Tillitslaust": 2,
    "bákn": 2,
    "Hallgrímsdóttir": 2,
    "rændir": 2,
    "Halldór": 2,
    "ENSKI": 2,
    "BOLTINN": 2,
    "féllu": 2,
    "ALBUMM": 2,
    "Már": 2,
    "Teigurinn": 2,
    "skrifar": 2,
    "lögregluþjónsins": 2,
    "eins": 2,
    "körfubolta": 2,
    "röð": 2,
    "Golf": 2,
    "ára": 2,
    "komast": 2,
    "inn": 2,
    "segir": 9,
    "Það": 4,
    "Enn": 3,
    "Íslandi": 90,
    "ferðaþjónustunnar": 90,
    "hrun": 90,
    "ferðaþjónustu": 90,
    "hefur": 93,
    "krónunnar": 90,
    "út": 36,
    "ég": 34,
    "koma": 91,
    "eða": 91,
    "enn": 18,
    "statt": 95,
    "vanda": 95,
    "óljóst": 90,
    "hvernig": 90,
    "kísilverið": 82,
    "borga": 94,
    "air": 88,
    "eina": 88,
    "flugfélagið": 88,
    "rukka": 88,
    "handfarangur": 88,
    "Leifsstöð": 88,
    "Innkoma": 94,
    "Costco": 94,
    "úrslitaatriði": 94,
    "Vill": 83,
    "sýni": 83,
    "lágmarks": 83,
    "sanngirni": 83,
    "Hlutabréf": 96,
    "verulega": 95,
    "Met": 58,
    "hvalaskoðun": 58,
    "útlit": 58,
    "lægð": 58,
    "Eignir": 87,
    "stýringu": 87,
    "lækkuðu": 87,
    "ráðin": 77,
    "nýr": 77,
    "viðskiptastjóri": 77,
    "Akureyri": 77,
    "Engar": 94,
    "Regus": 77,
    "áherslubreytingar": 94,
    "nýjum": 94,
    "eigendum": 94,
    "Dominos": 94,
    "Svarnir": 3,
    "loksins": 3,
    "nótt": 3,
    "óvinir": 3,
    "upplifað": 3,
    "mikið": 3,
    "hatur": 3,
    "mætast": 3,
    "Druslugöngunni": 3,
    "Ed": 3,
    "dýpstu": 3,
    "sundlaug": 3,
    "hélt": 3,
    "niðri": 3,
    "botninn": 3,
    "Kafaði": 3,
    "tímann": 3,
    "andanum": 3,
    "viðtöl": 3,
    "Ísland": 3,
    "Belgía": 3,
    "kvöddu": 3,
    "sigri": 3,
    "Strákarnir": 3,
    "spila": 3,
    "áfram": 3,
    "Fastir": 3,
    "pennar": 3,
    "Þú": 3,
    "okkur": 3,
    "0600": 3,
    "séu": 120,
    "Þórir": 120,
    "eru": 125,
    "það": 123,
    "lækka": 125,
    "lesið": 123,
    "Mest": 123,
    "Landsbankinn": 115,
    "Erlent": 4,
    "hættum": 4,
    "embættismann": 4,
    "heimabæ": 4,
    "kynferðislega": 4,
    "Mér": 4,
    "fannst": 4,
    "þakklát": 4,
    "Kærði": 4,
    "áreitni": 4,
    "þarf": 4,
    "LÍFIÐ": 4,
    "jafn": 4,
    "heims": 4,
    "allan": 4,
    "Íþróttafréttir": 4,
    "verið": 95,
    "milljarða": 157,
    "slyss": 5,
    "klikka": 5,
    "deila": 5,
    "Þyrlan": 5,
    "beita": 5,
    "ofbeldi": 5,
    "boltinn": 5,
    "sigur": 5,
    "Enski": 5,
    "Körfubolti": 5,
    "Sport": 5,
    "sé": 181,
    "við": 230,
    "eftir": 183,
    "vegna": 130,
    "með": 194,
    "kölluð": 6,
    "vera": 6,
    "Fótbolti": 6,
    "Skoðun": 6,
    "mun": 208,
    "Icelandair": 222,
    "sem": 253,
    "hafa": 217,
    "Hættum": 9,
    "innlent": 21,
    "ekki": 434,
    "Innlent": 14,
    "eiga": 14,
    "fyrir": 353,
    "Tveir": 17,
    "Lífið": 17,
    "og": 569,
    "Marel": 18,
    "dregst": 18,
    "Hagnaður": 18,
    "saman": 18,
    "Viðskipti": 670,
    "Sturlaður": 26,
    "norskur": 26,
    "eldri": 26,
    "slasar": 26,
    "íslensk": 26,
    "hjón": 26,
    "maður": 27,
    "einræðisherra": 30,
    "gær": 30,
    "vef": 30,
    "KCNA": 30,
    "opinberri": 30,
    "fréttaveitu": 30,
    "örugg": 30,
    "reyni": 30,
    "þau": 30,
    "gera": 30,
    "árás": 30,
    "einræðisríkið.": 30,
    "helstu": 30,
    "einu": 30,
    "bandamenn": 30,
    "gagnrýnt": 30,
    "eldflaugaskotið.": 30,
    "forseti": 30,
    "Bæði": 30,
    "ógna": 30,
    "heiminum": 30,
    "væru": 30,
    "þessi": 30,
    "vopn": 30,
    "tilraunir": 30,
    "fallnar": 30,
    "einangra": 30,
    "frekar": 30,
    "skaða": 30,
    "efnahag": 30,
    "íbúum": 30,
    "frétt": 30,
    "samkvæmt": 30,
    "taka": 30,
    "öll": 30,
    "nauðsynleg": 30,
    "skref": 30,
    "tryggja": 30,
    "öryggi": 30,
    "bandamanna": 30,
    "Utanríkisráðuneyti": 30,
    "brjóta": 30,
    "myndu": 30,
    "samþykktum": 30,
    "þjóðanna": 30,
    "óskum": 30,
    "alþjóðasamfélagsins": 30,
    "hvatti": 30,
    "ráðuneytið": 30,
    "öryggisráðs": 30,
    "frekari": 30,
    "spennu": 30,
    "stillingu": 30,
    "nýjasta": 30,
    "Sameinuðu": 30,
    "yfirvöldum": 30,
    "tóninn": 30,
    "Twitter": 30,
    "lýsti": 30,
    "eldflaugar": 30,
    "vonbrigðum": 30,
    "aðgerðarleysi": 30,
    "yfirvalda": 30,
    "Forsetinn": 30,
    "forsetar": 30,
    "hagnast": 30,
    "leyft": 30,
    "hundruð": 30,
    "dala": 30,
    "gerðu": 30,
    "Kínverjar": 30,
    "hefðu": 30,
    "Þeir": 30,
    "munum": 30,
    "málum": 30,
    "leyfa": 30,
    "þessu": 30,
    "viðgangast": 30,
    "auðveldlega": 30,
    "leyst": 30,
    "tali": 30,
    "am": 30,
    "Our": 30,
    "past": 30,
    "yet..": 30,
    "...they": 30,
    "do": 30,
    "vandamál": 30,
    "NOTHING": 30,
    "for": 30,
    "us": 30,
    "just": 30,
    "We": 30,
    "will": 30,
    "no": 30,
    "Spenna": 30,
    "Tengdar": 30,
    "Íran": 30,
    "undanförnu": 30,
    "tilraunaskotsins": 30,
    "aukist": 30,
    "29.7.2017": 30,
    "boðaður": 30,
    "niðurstöður": 30,
    "NorðurKóreumenn": 30,
    "stóran": 30,
    "loft": 30,
    "hafnaði": 30,
    "langdrægum": 30,
    "Geta": 30,
    "skutu": 30,
    "þjóðaröryggisráði": 30,
    "næsta": 30,
    "Neyðarfundur": 30,
    "framkvæmt": 30,
    "næstu": 30,
    "annað": 30,
    "dögum": 30,
    "líklegt": 30,
    "eldflaugum": 30,
    "Talið": 30,
    "ári": 30,
    "25.7.2017": 30,
    "Hringdi": 30,
    "kyrkislanga": 30,
    "neyðarlínuna": 30,
    "föst": 30,
    "andlitinu": 30,
    "handteknir": 30,
    "Modi": 30,
    "ýmist": 30,
    "ræður": 30,
    "nýjan": 30,
    "hetja": 30,
    "Priebus": 30,
    "látinn": 30,
    "Narendra": 30,
    "misheppnað": 30,
    "Hryðjuverk": 30,
    "mótframbjóðanda": 30,
    "skúrkur": 30,
    "rán": 30,
    "starfsmannastjóra": 30,
    "niður": 31,
    "alla": 31,
    "viðkomandi": 31,
    "milli": 31,
    "innan": 31,
    "lög": 31,
    "Rússum": 31,
    "kominn": 31,
    "undirritar": 31,
    "refsiaðgerðir": 31,
    "ekkert": 32,
    "þess": 33,
    "aðila": 33,
    "yfir": 33,
    "sama": 34,
    "á": 71,
    "upprisinn": 35,
    "Sirkus": 35,
    "Þórshöfn": 35,
    "Færeyjum": 35,
    "góðan": 35,
    "orðstír": 35,
    "í": 116,
    "kæra": 58,
    "vatn": 58,
    "hey": 58,
    "flutt": 58,
    "Íslenskt": 58,
    "eldflaugaskot": 60,
    "sýna": 60,
    "ríkisins": 60,
    "eingöngu": 60,
    "landsins": 60,
    "svæðinu": 60,
    "sendi": 60,
    "tilraunaskot": 60,
    "Sérfræðingar": 60,
    "segja": 60,
    "skyn": 60,
    "gefa": 60,
    "to": 60,
    "of": 60,
    "—": 60,
    "@realDonaldTrump": 60,
    "NorðurKórea": 60,
    "Vilja": 60,
    "eldflaugavarnir": 60,
    "Norðurkóresk": 60,
    "mótmæli": 60,
    "28.7.2017": 60,
    "betrumbæta": 60,
    "nú": 61,
    "dag": 61,
    "gegn": 61,
    "gagnvart": 61,
    "skemma": 61,
    "partíið": 61,
    "Óttast": 61,
    "þolendur": 61,
    "kæru": 61,
    "Lést": 63,
    "flúðasiglingu": 63,
    "vilji": 63,
    "kvöld": 64,
    "Viðbúnaðarstig": 64,
    "hugsanlegs": 64,
    "Kötlugoss": 64,
    "stig": 64,
    "hækkað": 64,
    "tvisvar": 65,
    "Hvítá": 68,
    "nauðgað": 68,
    "þeirra": 90,
    "tilkynningu": 90,
    "sagði": 90,
    "Bandaríkjanna": 90,
    "sögð": 90,
    "gæti": 90,
    "skotið": 90,
    "landhelgi": 90,
    "eldflaug": 90,
    "öðrum": 93,
    "endanum": 93,
    "húsinu": 93,
    "Hvíta": 93,
    "Hryðjuverkamenn": 93,
    "ætluðu": 93,
    "granda": 93,
    "flugvél": 93,
    "ætla": 118,
    "Íranar": 118,
    "eldflaugatilraunum": 118,
    "JongUn": 119,
    "færi": 119,
    "gervöll": 119,
    "Category": 120,
    "sér": 130,
    "sínum": 152,
    "Kína": 210,
    "Trump": 211,
    "Bandaríkin": 239,
    "NorðurKóreu": 270
}